designate/__init__.py
designate/context.py
designate/coordination.py
designate/dnsmiddleware.py
designate/dnsutils.py
designate/exceptions.py
designate/heartbeat_emitter.py
designate/i18n.py
designate/notifications.py
designate/plugin.py
designate/policy.py
designate/rpc.py
designate/schema.py
designate/service.py
designate/utils.py
designate/version.py
designate/api/__init__.py
designate/api/middleware.py
designate/api/service.py
designate/api/versions.py
designate/api/wsgi.py
designate/api/admin/__init__.py
designate/api/admin/app.py
designate/api/admin/controllers/__init__.py
designate/api/admin/controllers/root.py
designate/api/admin/controllers/extensions/__init__.py
designate/api/admin/controllers/extensions/counts.py
designate/api/admin/controllers/extensions/export.py
designate/api/admin/controllers/extensions/quotas.py
designate/api/admin/controllers/extensions/reports.py
designate/api/admin/controllers/extensions/tenants.py
designate/api/admin/controllers/extensions/zones.py
designate/api/admin/views/__init__.py
designate/api/admin/views/base.py
designate/api/admin/views/extensions/__init__.py
designate/api/admin/views/extensions/quotas.py
designate/api/admin/views/extensions/reports.py
designate/api/v2/__init__.py
designate/api/v2/app.py
designate/api/v2/patches.py
designate/api/v2/controllers/__init__.py
designate/api/v2/controllers/blacklists.py
designate/api/v2/controllers/common.py
designate/api/v2/controllers/errors.py
designate/api/v2/controllers/floatingips.py
designate/api/v2/controllers/limits.py
designate/api/v2/controllers/pools.py
designate/api/v2/controllers/quotas.py
designate/api/v2/controllers/recordsets.py
designate/api/v2/controllers/rest.py
designate/api/v2/controllers/reverse.py
designate/api/v2/controllers/root.py
designate/api/v2/controllers/service_status.py
designate/api/v2/controllers/tlds.py
designate/api/v2/controllers/tsigkeys.py
designate/api/v2/controllers/zones/__init__.py
designate/api/v2/controllers/zones/nameservers.py
designate-21.0.0.dist-info/AUTHORS
designate-21.0.0.dist-info/LICENSE
designate-21.0.0.dist-info/METADATA
designate-21.0.0.dist-info/WHEEL
designate-21.0.0.dist-info/entry_points.txt
designate-21.0.0.dist-info/pbr.json
designate-21.0.0.dist-info/top_level.txt
designate-21.0.0.dist-info/RECORD
